phiddipus/__init__.py
phiddipus/cli.py
phiddipus/nvdRequests.py
phiddipus/vulnerabilityScanner.py
phiddipus-1.0.0.dist-info/licenses/LICENSE
phiddipus-1.0.0.dist-info/METADATA
phiddipus-1.0.0.dist-info/WHEEL
phiddipus-1.0.0.dist-info/entry_points.txt
phiddipus-1.0.0.dist-info/top_level.txt
phiddipus-1.0.0.dist-info/RECORD
